{
	"calculetor": {
		"name": "calculeter",
		"title": "calculeter",
		"path": "/calculetor"
	},
	"canP-circular-motion": {
		"name": "Round",
		"title": "canP-circular-motion",
		"path": "/canP-circular-motion"
	},
	"colorConvarter": {
		"name": "color",
		"title": "colorConvarter",
		"path": "/colorConvarter"
	},
	"partica-demo": {
		"name": "partical",
		"title": "partica-demo",
		"path": "/partica-demo"
	},
	"randomWalk": {
		"name": "randomWalk",
		"title": "randomWalk",
		"path": "/randomWalk"
	},
	"sterShawor": {
		"name": "sterShawor",
		"title": "sterShawor",
		"path": "/sterShawor"
	},
	"test": {
		"name": "test",
		"title": "test",
		"path": "/test"
	},
	"chaos-game": {
		"name": "chaos-game",
		"title": "Chaos Game",
		"path": "/chaos-game"
	}
}